Workbook
Name aporte: DIO_FINANCE!$D$20
Name patrimonio: DIO_FINANCE!$D$23
Name periodo: DIO_FINANCE!$D$21
Name rendimento_carteira: DIO_FINANCE!$D$16
Name salario: DIO_FINANCE!$D$15
Name sugest_invest: DIO_FINANCE!$D$17
Name taxa_mensal: DIO_FINANCE!$D$22

Sheet DIO_FINANCE
B14: CONFIGURAÇÕES
B15: Salário | D15: 2000
B16: Rendimento Carteira | D16: 0.006
B17: Sugestão de Investimento | D17: =D15*30% -> 600
B19: INVESTIMENTO MENSAL
B20: Quanto Investir Por Mês? | D20: 200
B21: Por Quantos Anos? | D21: 5
B22: Taxa de Rendimento Mensal? | D22: 0.01079
B23: Patrimônio Acumulado? | D23: =FV(taxa_mensal,periodo*12,aporte*-1) -> 16755.383
B24: Dividendos Mensais? | D24: =patrimonio*$D$16 -> 100.5323
B26: CENÁRIOS | D26: DIVIDENDO
A27: 2 | B27: Quanto em 2 Anos? | C27: =FV($D$22,$A27*12,$D$20*-1) -> 5445.5255 | D27: =C27*rendimento_carteira -> 32.673153
A28: 5 | B28: Quanto em 5 Anos? | C28: =FV($D$22,$A28*12,$D$20*-1) -> 16755.383 | D28: =C28*rendimento_carteira -> 100.5323
A29: 10 | B29: Quanto em 10 Anos? | C29: =FV($D$22,$A29*12,$D$20*-1) -> 48656.843 | D29: =C29*rendimento_carteira -> 291.94106
A30: 20 | B30: Quanto em 20 Anos? | C30: =FV($D$22,$A30*12,$D$20*-1) -> 225039.68 | D30: =C30*rendimento_carteira -> 1350.2381
A31: 30 | B31: Quanto em 30 Anos? | C31: =FV($D$22,$A31*12,$D$20*-1) -> 864433.93 | D31: =C31*rendimento_carteira -> 5186.6036
B33: PERFIL | C33: AGRESSIVO
B34: Valor a ser investido por mês | C34: =aporte -> 200
B36: TIPO DE FII | C36: PERCENTUAL SUGERIDO | D36: VALORES
B37: Papel | C37: =VLOOKUP($C$33&"-"&B37,TAB_APOIO!$A:$D,4,FALSE) -> 0.5 | D37: =C37*$C$34 -> 100
B38: Tijolo | C38: =VLOOKUP($C$33&"-"&B38,TAB_APOIO!$A:$D,4,FALSE) -> 0.1 | D38: =C38*$C$34 -> 20
B39: Hibridos | C39: =VLOOKUP($C$33&"-"&B39,TAB_APOIO!$A:$D,4,FALSE) -> 0.05 | D39: =C39*$C$34 -> 10
B40: FOFs | C40: =VLOOKUP($C$33&"-"&B40,TAB_APOIO!$A:$D,4,FALSE) -> 0.05 | D40: =C40*$C$34 -> 10
B41: Desenvolvimento | C41: =VLOOKUP($C$33&"-"&B41,TAB_APOIO!$A:$D,4,FALSE) -> 0.2 | D41: =C41*$C$34 -> 40
B42: Hotelarias | C42: =VLOOKUP($C$33&"-"&B42,TAB_APOIO!$A:$D,4,FALSE) -> 0.1 | D42: =C42*$C$34 -> 20
D43: =SUM(D37:D42) -> 200

Sheet TAB_APOIO
A3: CHAVE | B3: PERFIL | C3: TIPO DE FII | D3: %
A4: =B4&"-"&C4 -> Conservador-Papel | B4: Conservador | C4: Papel | D4: 0.3
A5: =B5&"-"&C5 -> Conservador-Tijolo | B5: Conservador | C5: Tijolo | D5: 0.5
A6: =B6&"-"&C6 -> Conservador-Hibridos | B6: Conservador | C6: Hibridos | D6: 0.1
A7: =B7&"-"&C7 -> Conservador-FOFs | B7: Conservador | C7: FOFs | D7: 0.1
A8: =B8&"-"&C8 -> Conservador-Desenvolvimento | B8: Conservador | C8: Desenvolvimento | D8: 0
A9: =B9&"-"&C9 -> Conservador-Hotelarias | B9: Conservador | C9: Hotelarias | D9: 0
A10: =B10&"-"&C10 -> Moderado-Papel | B10: Moderado | C10: Papel | D10: 0.32
A11: =B11&"-"&C11 -> Moderado-Tijolo | B11: Moderado | C11: Tijolo | D11: 0.3
A12: =B12&"-"&C12 -> Moderado-Hibridos | B12: Moderado | C12: Hibridos | D12: 0.08
A13: =B13&"-"&C13 -> Moderado-FOFs | B13: Moderado | C13: FOFs | D13: 0.1
A14: =B14&"-"&C14 -> Moderado-Desenvolvimento | B14: Moderado | C14: Desenvolvimento | D14: 0.1
A15: =B15&"-"&C15 -> Moderado-Hotelarias | B15: Moderado | C15: Hotelarias | D15: 0.1
... A21: =B21&"-"&C21 -> Agressivo-Hotelarias | B21: Agressivo | C21: Hotelarias | D21: 0.1
